invenio_iiif/__init__.py
invenio_iiif/config.py
invenio_iiif/ext.py
invenio_iiif/handlers.py
invenio_iiif/previewer.py
invenio_iiif/tasks.py
invenio_iiif/utils.py
invenio_iiif/version.py
invenio_iiif/templates/invenio_iiif/base.html
invenio_iiif/templates/invenio_iiif/preview.html
invenio_iiif-1.2.0.dist-info/AUTHORS.rst
invenio_iiif-1.2.0.dist-info/LICENSE
invenio_iiif-1.2.0.dist-info/METADATA
invenio_iiif-1.2.0.dist-info/WHEEL
invenio_iiif-1.2.0.dist-info/entry_points.txt
invenio_iiif-1.2.0.dist-info/top_level.txt
invenio_iiif-1.2.0.dist-info/RECORD
