Metadata-Version: 2.1
Name: invenio-iiif
Version: 1.2.0
Summary: IIIF API for Invenio.
Home-page: https://github.com/inveniosoftware/invenio-iiif
Author: CERN
Author-email: info@inveniosoftware.org
License: MIT
Keywords: invenio IIIF
Platform: any
Classifier: Environment :: Web Environment
Classifier: Intended Audience :: Developers
Classifier: License :: OSI Approved :: MIT License
Classifier: Operating System :: OS Independent
Classifier: Programming Language :: Python
Classifier: Topic :: Internet :: WWW/HTTP :: Dynamic Content
Classifier: Topic :: Software Development :: Libraries :: Python Modules
Classifier: Programming Language :: Python :: 2
Classifier: Programming Language :: Python :: 2.7
Classifier: Programming Language :: Python :: 3
Classifier: Programming Language :: Python :: 3.5
Classifier: Development Status :: 5 - Production/Stable
Requires-Dist: Flask-IIIF (>=0.6.1)
Requires-Dist: invenio-access (>=1.4.2)
Requires-Dist: invenio-base (>=1.2.5)
Requires-Dist: invenio-celery (>=1.2.3)
Requires-Dist: invenio-files-rest (>=1.3.0)
Requires-Dist: invenio-records-files (>=1.0.0)
Requires-Dist: Wand (>=0.4.4)
Provides-Extra: all
Requires-Dist: Sphinx (<3.4,>=3.3.1) ; extra == 'all'
Requires-Dist: invenio-db[postgresql,versioning] (>=1.0.9) ; extra == 'all'
Requires-Dist: pytest-invenio (>=1.4.2) ; extra == 'all'
Provides-Extra: docs
Requires-Dist: Sphinx (<3.4,>=3.3.1) ; extra == 'docs'
Provides-Extra: tests
Requires-Dist: invenio-db[postgresql,versioning] (>=1.0.9) ; extra == 'tests'
Requires-Dist: pytest-invenio (>=1.4.2) ; extra == 'tests'
